morwlox123/__init__.py
morwlox123/fart.py
morwlox123/pesnya.py
morwlox123-1.4.89.dist-info/METADATA
morwlox123-1.4.89.dist-info/WHEEL
morwlox123-1.4.89.dist-info/top_level.txt
morwlox123-1.4.89.dist-info/RECORD
