Metadata-Version: 2.4
Name: morwlox123
Version: 1.4.89
Summary: lox lox lox pon.
Home-page: https://m0rwi.ru
Author: m0rwyak
Author-email: itzm3gap0n@gmail.com
Project-URL: GitHub, https://github.com/gualf5ve/morwlox123
Keywords: files speedfiles
Requires-Python: >=3.6
Dynamic: author
Dynamic: author-email
Dynamic: description
Dynamic: description-content-type
Dynamic: home-page
Dynamic: keywords
Dynamic: project-url
Dynamic: requires-python
Dynamic: summary
